csv_to_db_package/__init__.py
csv_to_db_package/crud_operations_db.py
csv_to_db_package/csv_to_db.py
csv_to_db_yogeshwar-0.0.1.dist-info/LICENSE
csv_to_db_yogeshwar-0.0.1.dist-info/METADATA
csv_to_db_yogeshwar-0.0.1.dist-info/WHEEL
csv_to_db_yogeshwar-0.0.1.dist-info/top_level.txt
csv_to_db_yogeshwar-0.0.1.dist-info/RECORD
